telesto/__init__.py
telesto/api/__init__.py
telesto/api/telesto.py
telesto/app_services/__init__.py
telesto/app_services/topology_directory.py
telesto/app_services/topology_runner.py
telesto/apps/__init__.py
telesto/apps/topology_application.js
telesto/apps/topology_designer.html
telesto/apps/topology_designer.js
telesto/apps/topology_directory.html
telesto/apps/topology_directory.js
telesto/apps/common/__init__.py
telesto/apps/common/topology_engine.js
telesto/apps/common/topology_store.js
telesto/cli/__init__.py
telesto/cli/main.py
telesto/cli/telesto_defaults.toml
telesto/cli/collection1/extent.json
telesto/cli/collection1/metadata.json
telesto/cli/collection2/extent.json
telesto/cli/collection3/extent.json
telesto/cli/primary_workspace_folder/aaaaa/topology.json
telesto/cli/primary_workspace_folder/aaaaa/node/n64cf58_126404/properties.json
telesto/cli/primary_workspace_folder/aaaaa/node/n64d6a1_c09bc4/properties.json
telesto/cli/primary_workspace_folder/aaaaa/node/n64e6d8_c2993f/properties.json
telesto/cli/primary_workspace_folder/aaaaa/node/nd7f640_d6005d/properties.json
telesto/cli/primary_workspace_folder/bbbb/topology.json
telesto/cli/primary_workspace_folder/bbbb/node/naf69ec_011716/properties.json
telesto/cli/primary_workspace_folder/bbbb/node/nb0444a_84aa71/properties.json
telesto/cli/primary_workspace_folder/bbbb/node/nb23d3c_11f3fe/properties.json
telesto/cli/primary_workspace_folder/demo_ndvi/topology.json
telesto/cli/primary_workspace_folder/demo_ndvi/node/n8abea8_da63ca/properties.json
telesto/cli/primary_workspace_folder/demo_ndvi/node/n8c1b9c_4ebbb7/properties.json
telesto/cli/primary_workspace_folder/demo_ndvi/node/n8c678b_9e3e2c/properties.json
telesto/cli/primary_workspace_folder/demo_ndvi/node/na09b6b_604a02/properties.json
telesto/cli/primary_workspace_folder/demo_ndvi/node/na216f3_5dd068/properties.json
telesto/cli/primary_workspace_folder/demo_ndvi/node/na3a42a_e41d1a/properties.json
telesto-0.1.3.dist-info/licenses/LICENSE
telesto-0.1.3.dist-info/METADATA
telesto-0.1.3.dist-info/WHEEL
telesto-0.1.3.dist-info/entry_points.txt
telesto-0.1.3.dist-info/top_level.txt
telesto-0.1.3.dist-info/RECORD
