Metadata-Version: 2.4
Name: telesto
Version: 0.1.3
Summary: Telesto - a visual graph editor - based on Skadi, Narvi and Hyrrokkin
Author-email: Visual Topology <dev@visualtopology.com>
License-Expression: MIT
Project-URL: Homepage, https://visualtopology.org/telesto
Project-URL: Documentation, https://visualtopology.org/telesto
Project-URL: Repository, https://codeberg.org/visual-topology/telesto
Project-URL: Issues, https://codeberg.org/visual-topology/telesto/issues
Project-URL: Changelog, https://codeberg.org/visual-topology/telesto/src/branch/main/CHANGELOG.md
Classifier: Programming Language :: Python :: 3
Classifier: Programming Language :: JavaScript
Classifier: Operating System :: POSIX :: Linux
Classifier: Topic :: Software Development :: Libraries :: Application Frameworks
Classifier: Development Status :: 3 - Alpha
Requires-Python: >=3.11
License-File: LICENSE
Requires-Dist: narvi
Requires-Dist: hyrrokkin
Provides-Extra: tornado
Requires-Dist: tornado; extra == "tornado"
Dynamic: license-file
